transformers_app/__init__.py
transformers_app/utils.py
transformers_app/daemon/__init__.py
transformers_app/daemon/macos.py
transformers_app/settings/__init__.py
transformers_app/settings/attention_implementations.py
transformers_app/settings/devices.py
transformers_app/settings/quantizations.py
transformers_app/settings/settings.py
transformers_app/static/favicon.png
transformers_app/static/index.css
transformers_app/static/index.html
transformers_app/static/index.js
transformers_app/tray/__init__.py
transformers_app/tray/macos.py
transformers_app-0.1.0.dist-info/licenses/LICENSE
transformers_app-0.1.0.dist-info/METADATA
transformers_app-0.1.0.dist-info/WHEEL
transformers_app-0.1.0.dist-info/top_level.txt
transformers_app-0.1.0.dist-info/RECORD
