Metadata-Version: 2.4
Name: transformers-app
Version: 0.1.0
Summary: Transformers app
Author: Lysandre Debut
License: Copyright 2018- The Hugging Face team. All rights reserved.
Requires-Python: >=3.10
License-File: LICENSE
Requires-Dist: pyobjc
Requires-Dist: httpx
Provides-Extra: quality
Requires-Dist: ruff==0.13.1; extra == "quality"
Dynamic: license-file
